playingwithfusion/__init__.py
playingwithfusion/pwf.cpp
playingwithfusion/py.typed
playingwithfusion/version.py
playingwithfusion/_init__playingwithfusion.py
playingwithfusion/_playingwithfusion.cpython-311-aarch64-linux-gnu.so
playingwithfusion/_playingwithfusion.pyi
playingwithfusion/playingwithfusion.pc
playingwithfusion/trampolines/pwf__CANVenom.hpp
playingwithfusion/trampolines/pwf__TMD37003.hpp
playingwithfusion/trampolines/pwf__TimeOfFlight.hpp
robotpy_playingwithfusion-2026.1.16.dist-info/METADATA
robotpy_playingwithfusion-2026.1.16.dist-info/WHEEL
robotpy_playingwithfusion-2026.1.16.dist-info/entry_points.txt
robotpy_playingwithfusion-2026.1.16.dist-info/RECORD
