Metadata-Version: 2.4
Name: robotpy-playingwithfusion
Version: 2026.1.16
Summary: PlayingWithFusion for RobotPy
Project-URL: Source code, https://github.com/robotpy/robotpy-playingwithfusion
Author-email: RobotPy Development Team <robotpy@googlegroups.com>
License-Expression: BSD-3-Clause
Requires-Dist: wpilib<2027.0.0,>=2026.1.1
